salesdredge/__init__.py
salesdredge/__main__.py
salesdredge/helpers.py
salesdredge/crawler/__init__.py
salesdredge/crawler/helpers.py
salesdredge/crawler/indexer.py
salesdredge/crawler/scraper.py
salesdredge/report_builder/__init__.py
salesdredge-1.0.4.dist-info/METADATA
salesdredge-1.0.4.dist-info/WHEEL
salesdredge-1.0.4.dist-info/entry_points.txt
salesdredge-1.0.4.dist-info/top_level.txt
salesdredge-1.0.4.dist-info/RECORD
