Metadata-Version: 2.1
Name: salesdredge
Version: 1.0.4
Summary: This is the API for the Salesdredge.
Home-page: http://www.salesdredge.com
Author: Christopher Roos
Author-email: roos.christopher@gmail.com
License: MIT
Platform: UNKNOWN
Classifier: License :: OSI Approved :: MIT License
Classifier: Programming Language :: Python :: 3
Classifier: Programming Language :: Python :: 3.9
Requires-Dist: beautifulsoup4 (==4.9.3)
Requires-Dist: boto3 (==1.18.18)
Requires-Dist: botocore (==1.21.18)
Requires-Dist: bs4 (==0.0.1)
Requires-Dist: certifi (==2021.5.30)
Requires-Dist: charset-normalizer (==2.0.4)
Requires-Dist: elasticsearch (==7.13.1)
Requires-Dist: filelock (==3.0.12)
Requires-Dist: idna (==3.2)
Requires-Dist: jmespath (==0.10.0)
Requires-Dist: numpy (==1.21.1)
Requires-Dist: pandas (==1.3.1)
Requires-Dist: phonenumbers (==8.12.29)
Requires-Dist: python-dateutil (==2.8.2)
Requires-Dist: pytz (==2021.1)
Requires-Dist: requests (==2.26.0)
Requires-Dist: requests-file (==1.5.1)
Requires-Dist: s3transfer (==0.5.0)
Requires-Dist: six (==1.16.0)
Requires-Dist: soupsieve (==2.2.1)
Requires-Dist: tldextract (==3.1.0)
Requires-Dist: urllib3 (==1.26.6)
